<?xml version="1.0" encoding="utf-8" ?>
<dwsync>
<file name="About.html" server="92.205.9.236" local="133029857729529997" remote="133029597000000000" Dst="2" />
<file name="Collections.html" server="92.205.9.236" local="133029858080805923" remote="133029597000000000" Dst="2" />
<file name="Contact.html" server="92.205.9.236" local="133029858080805923" remote="133029597000000000" Dst="2" />
<file name="Exhibitions.html" server="92.205.9.236" local="133029858080805923" remote="133029597000000000" Dst="2" />
<file name="text_catalogues.html" server="92.205.9.236" local="133029858080805923" remote="133029597000000000" Dst="2" />
<file name="About.html" server="92.205.9.236/public_html/" local="133044739856294726" remote="133045935600000000" Dst="2" />
<file name="Collections.html" server="92.205.9.236/public_html/" local="133044802773356526" remote="133045935600000000" Dst="2" />
<file name="Contact.html" server="92.205.9.236/public_html/" local="133044413022347519" remote="133045935600000000" Dst="2" />
<file name="Exhibitions.html" server="92.205.9.236/public_html/" local="133044830697212529" remote="133045935600000000" Dst="2" />
<file name="text_catalogues.html" server="92.205.9.236/public_html/" local="133046261201371451" remote="133045974600000000" Dst="2" />
</dwsync>